ps/__init__.py
ps/job.py
metaspore/demo.py
metaspore/initializer.py
metaspore/loss_utils.py
metaspore/_metaspore.cpython-39-x86_64-linux-gnu.so
metaspore/model.py
metaspore/network_utils.py
metaspore/distributed_trainer.py
metaspore/__init__.py
metaspore/feature_group.py
metaspore/stack_trace_utils.py
metaspore/job_utils.py
metaspore/two_tower_retrieval.py
metaspore/two_tower_ranking.py
metaspore/agent.py
metaspore/patching_pickle.py
metaspore/embedding.py
metaspore/swing_retrieval.py
metaspore/url_utils.py
metaspore/spark.py
metaspore/input.py
metaspore/file_utils.py
metaspore/schema_utils.py
metaspore/estimator.py
metaspore/name_utils.py
metaspore/ps_launcher.py
metaspore/output.py
metaspore/updater.py
metaspore/experiment.py
metaspore/metric.py
metaspore/shell_utils.py
metaspore/distributed_tensor.py
metaspore/cast.py
metaspore/s3_utils.py
metaspore/nn/deep_fm.py
metaspore/nn/__init__.py
metaspore/nn/fm.py
metaspore/nn/wide_and_deep.py
metaspore/nn/normalization.py
metaspore/compat/__init__.py
metaspore/compat/ps/__init__.py
metaspore/algos/layers.py
metaspore/algos/dcn_v2_net.py
metaspore/algos/autoint_net.py
metaspore/algos/__init__.py
metaspore/algos/xdeepfm_net.py
metaspore/algos/ffm_net.py
metaspore/algos/widedeep_net.py
metaspore/algos/pnn_net.py
metaspore/algos/item_cf_retrieval.py
metaspore/algos/deepfm_net.py
metaspore/algos/dcn_net.py
metaspore/algos/fwfm_net.py
metaspore/algos/twotower/__init__.py
metaspore/algos/twotower/simplex/__init__.py
metaspore/algos/twotower/simplex/simplex_agent.py
metaspore/algos/twotower/simplex/simplex_net.py
metaspore/algos/twotower/dssm/dssm_net.py
metaspore/algos/twotower/dssm/__init__.py
metaspore/algos/twotower/dssm/dssm_agent.py
metaspore/algos/feature/target_encoder.py
metaspore/algos/feature/sequential_encoder.py
metaspore/algos/feature/__init__.py
metaspore/algos/feature/neg_sampler.py
metaspore/algos/feature/woe_encoder.py
metaspore-1.1.0.dist-info/METADATA
metaspore-1.1.0.dist-info/RECORD
metaspore-1.1.0.dist-info/LICENSE
metaspore-1.1.0.dist-info/WHEEL
metaspore-1.1.0.dist-info/top_level.txt
