Metadata-Version: 2.1
Name: metaspore
Version: 1.1.0
Summary: Metaspore: A Unified End-to-end Machine Intelligence Platform
Author: DMetaSoul
Author-email: opensource@dmetasoul.com
License: Apache-2.0
Project-URL: repository, https://github.com/meta-soul/MetaSpore
Keywords: training,ai,machinelearning,deeplearning,pytorch,spark,pyspark
Classifier: Programming Language :: Python :: 3
Classifier: License :: OSI Approved :: Apache Software License
Classifier: Operating System :: POSIX :: Linux
Classifier: Topic :: Scientific/Engineering :: Artificial Intelligence
Requires-Python: >=3.8
License-File: LICENSE
Requires-Dist: numpy (~=1.23.2)
Requires-Dist: pandas (~=1.4.3)
Requires-Dist: findspark (~=2.0.1)
Requires-Dist: cloudpickle (~=2.1.0)
Requires-Dist: nest-asyncio (~=1.5.5)
Requires-Dist: attrs (~=22.1.0)
Requires-Dist: cattrs (~=22.1.0)
Requires-Dist: PyYAML (~=5.4.1)
Requires-Dist: tabulate (~=0.8.10)
Requires-Dist: pyarrow (==7.0.0)
Requires-Dist: botocore (==1.24.21)
Requires-Dist: boto3 (==1.21.21)
Requires-Dist: awscli (==1.22.76)
Requires-Dist: awscli-plugin-endpoint (~=0.4)
Requires-Dist: fsspec[s3] (~=2022.7.1)
Requires-Dist: s3fs (~=2022.7.1)
Requires-Dist: python-consul (~=1.1.0)
Requires-Dist: faiss-cpu (~=1.7.2)
Requires-Dist: pymilvus (~=2.1.1)
Requires-Dist: pymongo (~=4.2.0)
